daterange/__init__.py
daterange/daterange.py
daterange/daterange_deprecated.py
wolffuxae_daterange-0.0.6.dist-info/LICENSE
wolffuxae_daterange-0.0.6.dist-info/METADATA
wolffuxae_daterange-0.0.6.dist-info/WHEEL
wolffuxae_daterange-0.0.6.dist-info/RECORD
