Metadata-Version: 2.1
Name: wolffuxae-daterange
Version: 0.0.6
Summary: daterange functions
Author: ekl
Author-email: ekluxae@gmail.com
Requires-Python: >=3.10,<4.0
Classifier: Programming Language :: Python :: 3
Classifier: Programming Language :: Python :: 3.10
Classifier: Programming Language :: Python :: 3.11
Classifier: Programming Language :: Python :: 3.12
